src/__init__.py
src/config/__init__.py
src/config/datamodels.py
src/interfaces/__init__.py
src/interfaces/datarequests.py
src/interfaces/requests.py
src/interfaces/task.py
src/types/__init__.py
src/types/tasks.py
src/utils/__init__.py
src/utils/s3_helper.py
python_temporal-0.0.8.dist-info/METADATA
python_temporal-0.0.8.dist-info/WHEEL
python_temporal-0.0.8.dist-info/top_level.txt
python_temporal-0.0.8.dist-info/RECORD
