Metadata-Version: 2.1
Name: python-temporal
Version: 0.0.8
Summary: The description of the package
Home-page: http://www.example.com/
Author: X.X
Author-email: xx@example.com
License: LICENSE
Requires-Dist: temporal-python-sdk
Requires-Dist: boto3 (~=1.24.22)
Requires-Dist: PyYAML
Requires-Dist: pandas (~=1.4.3)
Requires-Dist: numpy
Requires-Dist: pydantic (~=1.9.1)
